<?xml version="1.0" encoding="utf-8"?>
<XnaContent xmlns:Factories="Space.ComponentSystem.Factories">
  <Asset Type="Factories:ShipFactory[]">
    <Item>
      <Name>Player</Name>
      <Texture>Textures/spaceshipB</Texture>
      <CollisionRadius>50</CollisionRadius>
      <ExperiencePoints>0</ExperiencePoints>
      <Attributes>
        <Item>10 Mass</Item>
        <Item>100 Health</Item>
        <Item>2.5 HealthRegeneration</Item>
        <Item>50 Energy</Item>
        <Item>0.5 EnergyRegeneration</Item>
        <Item>100 AccelerationForce</Item>
        <Item>20 RotationForce</Item>
      </Attributes>
      <Items>
        <Name>StarterFuselage</Name>
        <Item>
          <Name>StarterWing</Name>
          <Item>
            <Name>StarterWeapon</Name>
          </Item>
        </Item>
        <Item>
          <Name>StarterWing</Name>
          <Item>
            <Name>StarterWeapon</Name>
          </Item>
        </Item>
        <Item>
          <Name>StarterReactor</Name>
        </Item>
        <Item>
          <Name>StarterSensor</Name>
        </Item>
        <Item>
          <Name>StarterThruster</Name>
        </Item>
        <Item>
          <Name>StarterShield</Name>
        </Item>
      </Items>
    </Item>
    <Item>
      <Name>L1_AI_Ship</Name>
      <Texture>Textures/Stolen/Ships/broadsword_hftr</Texture>
      <CollisionRadius>25</CollisionRadius>
      <ItemPool>Starter</ItemPool>
      <ExperiencePoints>10</ExperiencePoints>
      <Attributes>
        <Item>10 Mass</Item>
        <Item>20 to 40 Health</Item>
        <Item>1 to 1.5 HealthRegeneration</Item>
        <Item>50 to 75 Energy</Item>
        <Item>0.5 to 1 EnergyRegeneration</Item>
        <Item>95 to 115 AccelerationForce</Item>
        <Item>15 to 20 RotationForce</Item>
      </Attributes>
      <Items>
        <Name>L1_AI_Fuselage</Name>
        <Item>
          <Name>L1_AI_Weapon</Name>
        </Item>
        <Item>
          <Name>L1_AI_Reactor</Name>
        </Item>
        <Item>
          <Name>L1_AI_Thruster</Name>
        </Item>
        <Item>
          <Name>L1_AI_Sensor</Name>
        </Item>
      </Items>
    </Item>
  </Asset>
</XnaContent>