<?xml version="1.0" encoding="utf-8" ?>
<XnaContent>
  <Asset Type="Space.Data.Profile">
    <Name>Player</Name>
    <Ship>
      <Name>Sparrow</Name>

      <CollisionRadius>15</CollisionRadius>
      <Texture>Textures/ship</Texture>

      <Hulls>
        <Item>
          <Attributes>
            <Item>50 Health</Item>
            <Item>0.05 HealthRegeneration</Item>
            <Item>10 Mass</Item>
          </Attributes>
        </Item>
      </Hulls>

      <Reactors>
        <Item>
          <Attributes>
            <Item>100 Energy</Item>
            <Item>5 Mass</Item>
          </Attributes>
        </Item>
      </Reactors>

      <Thrusters>
        <Item>
          <Attributes>
            <Item>1 AccelerationForce</Item>
            <Item>2 RotationForce</Item>
            <Item>5 Mass</Item>
          </Attributes>
          <EnergieConsumption>0.5</EnergieConsumption>
          <AccelerationForce>8</AccelerationForce>
        </Item>
      </Thrusters>

      <Weapons>
        <Item>
          <Texture>Textures/ship</Texture>
          <Sound>laser</Sound>
          <Cooldown>30</Cooldown>
          <EnergieConsumption>10</EnergieConsumption>
          <Projectiles>
            <Item>
              <Texture>Textures/ship</Texture>
              <CollisionRadius>3</CollisionRadius>
              <Damage>5</Damage>
              <InitialVelocity>10</InitialVelocity>
            </Item>
          </Projectiles>
        </Item>
      </Weapons>
    </Ship>
  </Asset>
</XnaContent>
